{"frames":{"Figure-Face-Walking0.png":{"frame":{"x":0,"y":0,"w":16,"h":16},"rotated":false,"trimmed":false,"spriteSourceSize":{"x":0,"y":0,"w":16,"h":16},"sourceSize":{"w":16,"h":16}},"Figure-Face-Walking1.png":{"frame":{"x":16,"y":0,"w":16,"h":16},"rotated":false,"trimmed":false,"spriteSourceSize":{"x":0,"y":0,"w":16,"h":16},"sourceSize":{"w":16,"h":16}},"Figure-Face-Walking2.png":{"frame":{"x":32,"y":0,"w":16,"h":16},"rotated":false,"trimmed":false,"spriteSourceSize":{"x":0,"y":0,"w":16,"h":16},"sourceSize":{"w":16,"h":16}},"Figure-Face-Walking3.png":{"frame":{"x":48,"y":0,"w":16,"h":16},"rotated":false,"trimmed":false,"spriteSourceSize":{"x":0,"y":0,"w":16,"h":16},"sourceSize":{"w":16,"h":16}}},"meta":{"app":"https://github.com/piskelapp/piskel/","version":"1.0","image":"Figure-Face-Walking.png","format":"RGBA8888","size":{"w":64,"h":16}}}